{
  "symbol": "MMM",
  "last_close": 143.99,
  "signal": 1,
  "xgb_rmse": 0.015457,
  "combined_rmse": 0.015455,
  "gp_improvement": 2e-06,
  "ci_coverage_pct": 97.59,
  "n_train": 12773,
  "n_test": 3194,
  "forecast": [
    {
      "date": "2026-03-30",
      "mean_close": 144.0987,
      "lower_bound": 138.4483,
      "upper_bound": 149.9797,
      "std_return": 0.020001,
      "mean_return": 0.000754
    },
    {
      "date": "2026-03-31",
      "mean_close": 144.2091,
      "lower_bound": 136.2777,
      "upper_bound": 152.6022,
      "std_return": 0.02,
      "mean_return": 0.000766
    },
    {
      "date": "2026-04-01",
      "mean_close": 144.3196,
      "lower_bound": 134.6592,
      "upper_bound": 154.6732,
      "std_return": 0.02,
      "mean_return": 0.000766
    },
    {
      "date": "2026-04-02",
      "mean_close": 144.4302,
      "lower_bound": 133.3257,
      "upper_bound": 156.4597,
      "std_return": 0.02,
      "mean_return": 0.000766
    },
    {
      "date": "2026-04-03",
      "mean_close": 144.5409,
      "lower_bound": 132.1738,
      "upper_bound": 158.0652,
      "std_return": 0.02,
      "mean_return": 0.000766
    },
    {
      "date": "2026-04-06",
      "mean_close": 144.6517,
      "lower_bound": 131.1507,
      "upper_bound": 159.5425,
      "std_return": 0.02,
      "mean_return": 0.000766
    },
    {
      "date": "2026-04-07",
      "mean_close": 144.7626,
      "lower_bound": 130.2248,
      "upper_bound": 160.9232,
      "std_return": 0.02,
      "mean_return": 0.000766
    },
    {
      "date": "2026-04-08",
      "mean_close": 144.8735,
      "lower_bound": 129.3758,
      "upper_bound": 162.2277,
      "std_return": 0.02,
      "mean_return": 0.000766
    },
    {
      "date": "2026-04-09",
      "mean_close": 144.9845,
      "lower_bound": 128.5894,
      "upper_bound": 163.4701,
      "std_return": 0.02,
      "mean_return": 0.000766
    },
    {
      "date": "2026-04-10",
      "mean_close": 145.0956,
      "lower_bound": 127.8553,
      "upper_bound": 164.6607,
      "std_return": 0.02,
      "mean_return": 0.000766
    },
    {
      "date": "2026-04-13",
      "mean_close": 145.2068,
      "lower_bound": 127.1657,
      "upper_bound": 165.8075,
      "std_return": 0.02,
      "mean_return": 0.000766
    },
    {
      "date": "2026-04-14",
      "mean_close": 145.3181,
      "lower_bound": 126.5146,
      "upper_bound": 166.9163,
      "std_return": 0.020001,
      "mean_return": 0.000766
    },
    {
      "date": "2026-04-15",
      "mean_close": 145.4295,
      "lower_bound": 125.8972,
      "upper_bound": 167.9921,
      "std_return": 0.020001,
      "mean_return": 0.000766
    },
    {
      "date": "2026-04-16",
      "mean_close": 145.5409,
      "lower_bound": 125.3096,
      "upper_bound": 169.0386,
      "std_return": 0.020001,
      "mean_return": 0.000766
    },
    {
      "date": "2026-04-17",
      "mean_close": 145.6525,
      "lower_bound": 124.7486,
      "upper_bound": 170.0592,
      "std_return": 0.020001,
      "mean_return": 0.000766
    },
    {
      "date": "2026-04-20",
      "mean_close": 145.7641,
      "lower_bound": 124.2115,
      "upper_bound": 171.0564,
      "std_return": 0.020001,
      "mean_return": 0.000766
    },
    {
      "date": "2026-04-21",
      "mean_close": 145.8758,
      "lower_bound": 123.696,
      "upper_bound": 172.0326,
      "std_return": 0.020001,
      "mean_return": 0.000766
    },
    {
      "date": "2026-04-22",
      "mean_close": 145.9876,
      "lower_bound": 123.2003,
      "upper_bound": 172.9896,
      "std_return": 0.020001,
      "mean_return": 0.000766
    },
    {
      "date": "2026-04-23",
      "mean_close": 146.0995,
      "lower_bound": 122.7227,
      "upper_bound": 173.9291,
      "std_return": 0.020001,
      "mean_return": 0.000766
    },
    {
      "date": "2026-04-24",
      "mean_close": 146.2114,
      "lower_bound": 122.2617,
      "upper_bound": 174.8527,
      "std_return": 0.020001,
      "mean_return": 0.000766
    }
  ],
  "sentiment_available": true,
  "fetched_at": "2026-03-30T01:22:34.339557"
}