{
  "symbol": "MOS",
  "last_close": 25.0,
  "signal": 2,
  "xgb_rmse": 0.030668,
  "combined_rmse": 0.030662,
  "gp_improvement": 5e-06,
  "ci_coverage_pct": 95.01,
  "n_train": 7532,
  "n_test": 1883,
  "forecast": [
    {
      "date": "2026-03-30",
      "mean_close": 25.1043,
      "lower_bound": 23.6319,
      "upper_bound": 26.6685,
      "std_return": 0.030222,
      "mean_return": 0.004164
    },
    {
      "date": "2026-03-31",
      "mean_close": 25.1959,
      "lower_bound": 23.1318,
      "upper_bound": 27.4442,
      "std_return": 0.030216,
      "mean_return": 0.003642
    },
    {
      "date": "2026-04-01",
      "mean_close": 25.2879,
      "lower_bound": 22.7746,
      "upper_bound": 28.0785,
      "std_return": 0.030216,
      "mean_return": 0.003643
    },
    {
      "date": "2026-04-02",
      "mean_close": 25.3802,
      "lower_bound": 22.4906,
      "upper_bound": 28.641,
      "std_return": 0.030216,
      "mean_return": 0.003643
    },
    {
      "date": "2026-04-03",
      "mean_close": 25.4728,
      "lower_bound": 22.253,
      "upper_bound": 29.1585,
      "std_return": 0.030216,
      "mean_return": 0.003643
    },
    {
      "date": "2026-04-06",
      "mean_close": 25.5658,
      "lower_bound": 22.048,
      "upper_bound": 29.6448,
      "std_return": 0.030216,
      "mean_return": 0.003643
    },
    {
      "date": "2026-04-07",
      "mean_close": 25.6591,
      "lower_bound": 21.8675,
      "upper_bound": 30.108,
      "std_return": 0.030216,
      "mean_return": 0.003642
    },
    {
      "date": "2026-04-08",
      "mean_close": 25.7527,
      "lower_bound": 21.7064,
      "upper_bound": 30.5533,
      "std_return": 0.030216,
      "mean_return": 0.003642
    },
    {
      "date": "2026-04-09",
      "mean_close": 25.8466,
      "lower_bound": 21.5608,
      "upper_bound": 30.9843,
      "std_return": 0.030216,
      "mean_return": 0.003642
    },
    {
      "date": "2026-04-10",
      "mean_close": 25.9409,
      "lower_bound": 21.4283,
      "upper_bound": 31.4038,
      "std_return": 0.030216,
      "mean_return": 0.003642
    },
    {
      "date": "2026-04-13",
      "mean_close": 26.0356,
      "lower_bound": 21.3068,
      "upper_bound": 31.8138,
      "std_return": 0.030216,
      "mean_return": 0.003641
    },
    {
      "date": "2026-04-14",
      "mean_close": 26.1305,
      "lower_bound": 21.1948,
      "upper_bound": 32.2157,
      "std_return": 0.030216,
      "mean_return": 0.003641
    },
    {
      "date": "2026-04-15",
      "mean_close": 26.2258,
      "lower_bound": 21.0911,
      "upper_bound": 32.6107,
      "std_return": 0.030216,
      "mean_return": 0.003641
    },
    {
      "date": "2026-04-16",
      "mean_close": 26.3215,
      "lower_bound": 20.9946,
      "upper_bound": 33.0,
      "std_return": 0.030216,
      "mean_return": 0.003641
    },
    {
      "date": "2026-04-17",
      "mean_close": 26.4175,
      "lower_bound": 20.9046,
      "upper_bound": 33.3842,
      "std_return": 0.030216,
      "mean_return": 0.00364
    },
    {
      "date": "2026-04-20",
      "mean_close": 26.5138,
      "lower_bound": 20.8204,
      "upper_bound": 33.7642,
      "std_return": 0.030216,
      "mean_return": 0.00364
    },
    {
      "date": "2026-04-21",
      "mean_close": 26.6105,
      "lower_bound": 20.7414,
      "upper_bound": 34.1403,
      "std_return": 0.030216,
      "mean_return": 0.00364
    },
    {
      "date": "2026-04-22",
      "mean_close": 26.7075,
      "lower_bound": 20.6672,
      "upper_bound": 34.5132,
      "std_return": 0.030216,
      "mean_return": 0.00364
    },
    {
      "date": "2026-04-23",
      "mean_close": 26.8049,
      "lower_bound": 20.5974,
      "upper_bound": 34.8833,
      "std_return": 0.030216,
      "mean_return": 0.003639
    },
    {
      "date": "2026-04-24",
      "mean_close": 26.9026,
      "lower_bound": 20.5315,
      "upper_bound": 35.2509,
      "std_return": 0.030216,
      "mean_return": 0.003639
    }
  ],
  "sentiment_available": true,
  "fetched_at": "2026-03-30T01:25:30.487645"
}